pqreader/__init__.py
pqreader/pqreader.py
pqreader-0.0.3.dist-info/LICENSE
pqreader-0.0.3.dist-info/METADATA
pqreader-0.0.3.dist-info/WHEEL
pqreader-0.0.3.dist-info/top_level.txt
pqreader-0.0.3.dist-info/RECORD
